{"is_source_file": true, "format": "JavaScript (React JSX)", "description": "React functional component for rendering the application's header, including the title and a theme toggle button. Uses a custom hook 'useSettings' to access and modify theme settings.", "external_files": ["../hooks/useSettings"], "external_methods": ["useSettings()"], "published": [], "classes": [], "methods": [{"name": "Header()", "description": "React functional component rendering the header with theme toggle functionality.", "scope": "", "scopeKind": ""}, {"name": "handleToggle", "description": "Function to toggle theme between 'light' and 'dark' by invoking 'setTheme' from context."}], "calls": ["useSettings()", "setTheme(nextTheme)"], "search-terms": ["Header component", "Theme toggle", "React functional component", "useSettings hook", "app-header"], "state": 2, "file_id": 21, "knowledge_revision": 50, "git_revision": "0a4ce56869ee79c9a799cf60fffd443c416ac2b3", "ctags": [{"_type": "tag", "name": "Header", "path": "/home/kavia/workspace/code-generation/local-notes-manager-185853-185873/frontend_react/src/components/Header.js", "pattern": "/^export default function Header() {$/", "language": "JavaScript", "kind": "function", "signature": "()"}, {"_type": "tag", "name": "Switch to ${nextTheme} mode", "path": "/home/kavia/workspace/code-generation/local-notes-manager-185853-185873/frontend_react/src/components/Header.js", "pattern": "/^            aria-label={`Switch to ${nextTheme} mode`}$/", "language": "JavaScript", "kind": "field", "scope": "Header.aria", "scopeKind": "class"}, {"_type": "tag", "name": "Switch to ${nextTheme} mode", "path": "/home/kavia/workspace/code-generation/local-notes-manager-185853-185873/frontend_react/src/components/Header.js", "pattern": "/^            title={`Switch to ${nextTheme} mode`}$/", "language": "JavaScript", "kind": "field", "scope": "Header.title", "scopeKind": "class"}, {"_type": "tag", "name": "handleToggle", "path": "/home/kavia/workspace/code-generation/local-notes-manager-185853-185873/frontend_react/src/components/Header.js", "pattern": "/^            onClick={handleToggle}$/", "language": "JavaScript", "kind": "field", "scope": "Header.onClick", "scopeKind": "class"}], "hash": "f01bf399f92fc5051b6c91b0a265351b", "format-version": 4, "code-base-name": "frontend_react", "filename": "frontend_react/src/components/Header.js", "fields": [{"name": "aria-label={`Switch to ${nextTheme} mode`}", "scope": "Header.aria", "scopeKind": "class", "description": "unavailable"}, {"name": "title={`Switch to ${nextTheme} mode`}", "scope": "Header.title", "scopeKind": "class", "description": "unavailable"}, {"name": "onClick={handleToggle}", "scope": "Header.onClick", "scopeKind": "class", "description": "unavailable"}], "revision_history": [{"50": "0a4ce56869ee79c9a799cf60fffd443c416ac2b3"}]}